Workbook

Sheet Budget Summary
A1: PROJECT BUDGET SUMMARY
A2: Bottoms-up build cost (pre-tax) — cross-references Resource Plan & Other Costs
A4: Cost Block | B4: Amount (₹) | C4: % of Pre-Tax Budget
A5: A. Personnel (delivery team) | B5: ='Resource Plan'!F17 -> 28280000 | C5: =B5/$B$9 -> 0.69864422
A6: B. Non-Personnel (infra, tools, integrations, marketing) | B6: ='Other Costs'!D14 -> 9200000 | C6: =B6/$B$9 -> 0.22728171
A7: Sub-Total (A + B) | B7: =B5+B6 -> 37480000 | C7: =B7/$B$9 -> 0.92592593
A8: Contingency / Management Reserve @ 8% | B8: =B7*0.08 -> 2998400 | C8: =B8/$B$9 -> 0.074074074
A9: TOTAL PROJECT BUDGET (Pre-Tax) | B9: =B7+B8 -> 40478400 | C9: =B9/$B$9 -> 1
A11: GST (18%) is shown in the client-facing Quotation sheet; it is recoverable as input tax credit and excluded from the internal build budget.

Sheet Phase Quotation
A1: PHASE-WISE QUOTATION
A2: Pre-tax budget allocated across delivery phases, plus GST to arrive at the all-inclusive quotation
A4: # | B4: Project Phase | C4: Key Deliverables | D4: Duration | E4: % of Budget | F4: Phase Cost (₹)
A5: 1 | B5: Initiation & Discovery | C5: Project charter, kickoff, governance setup, vision workshop | D5: Month 1 | E5: 0.04 | F5: =E5*'Budget Summary'!B9 -> 1619136
A6: 2 | B6: Requirements & Analysis | C6: BRD, SRS, FRD, process maps, backlog, RTM | D6: Months 1–2.5 | E6: 0.07 | F6: =E6*'Budget Summary'!B9 -> 2833488
A7: 3 | B7: UX / UI Design | C7: Wireframes, prototypes, design system, usability testing | D7: Months 2–3.5 | E7: 0.09 | F7: =E7*'Budget Summary'!B9 -> 3643056
A8: 4 | B8: Architecture & Environment Setup | C8: Solution architecture, CI/CD, cloud landing zone | D8: Months 2–3 | E8: 0.06 | F8: =E8*'Budget Summary'!B9 -> 2428704
A9: 5 | B9: Core Platform Development | C9: Catalog, search, cart, checkout, orders, accounts, admin | D9: Months 3–8 | E9: 0.34 | F9: =E9*'Budget Summary'!B9 -> 13762656
A10: 6 | B10: Supply Chain & Integrations | C10: Inventory/WMS, payments, logistics, ERP, notifications | D10: Months 5–8 | E10: 0.1 | F10: =E10*'Budget Summary'!B9 -> 4047840
A11: 7 | B11: Testing & QA | C11: Functional, regression, performance, security, automation | D11: Months 6–9 | E11: 0.09 | F11: =E11*'Budget Summary'!B9 -> 3643056
A12: 8 | B12: UAT, Security Audit & Deployment | C12: UAT, VAPT, performance sign-off, prod cut-over | D12: Months 9–10 | E12: 0.07 | F12: =E12*'Budget Summary'!B9 -> 2833488
A13: 9 | B13: Marketing & Go-Live | C13: Campaigns, ASO/SEO, launch, app-store release | D13: Months 9–11 | E13: 0.11 | F13: =E13*'Budget Summary'!B9 -> 4452624
A14: 10 | B14: Hypercare & Stabilization | C14: Production support, defect triage, handover | D14: Month 11 | E14: 0.03 | F14: =E14*'Budget Summary'!B9 -> 1214352
B15: Sub-Total (Pre-Tax) | E15: =SUM(E5:E14) -> 1 | F15: =SUM(F5:F14) -> 40478400
B16: GST @ 18% | F16: =F15*0.18 -> 7286112
B17: GRAND TOTAL QUOTATION (Incl. GST) | F17: =F15+F16 -> 47764512

Sheet Payment Schedule
A1: MILESTONE-LINKED PAYMENT / DISBURSEMENT SCHEDULE
A2: Disbursements released against milestone acceptance — % of all-inclusive quotation
A4: Milestone | B4: Acceptance Trigger | C4: Target | D4: % of Total | E4: Amount (₹)
A5: M0 – Mobilization | B5: Charter signed, team & governance mobilized | C5: Month 1 | D5: 0.1 | E5: =D5*'Phase Quotation'!F17 -> 4776451.2
A6: M1 – Requirements & Design Sign-off | B6: SRS, FRD & UX prototype approved | C6: Month 3.5 | D6: 0.15 | E6: =D6*'Phase Quotation'!F17 -> 7164676.8
A7: M2 – Architecture Baseline | B7: Architecture + CI/CD + Sprint 1–2 demo | C7: Month 4 | D7: 0.1 | E7: =D7*'Phase Quotation'!F17 -> 4776451.2
A8: M3 – MVP Feature-Complete (50%) | B8: Core commerce flows demoable in staging | C8: Month 6 | D8: 0.2 | E8: =D8*'Phase Quotation'!F17 -> 9552902.4
A9: M4 – Build Complete (100%) | B9: All features + integrations code-complete | C9: Month 8 | D9: 0.2 | E9: =D9*'Phase Quotation'!F17 -> 9552902.4
A10: M5 – QA & UAT Sign-off | B10: Test exit + UAT acceptance + VAPT closed | C10: Month 10 | D10: 0.12 | E10: =D10*'Phase Quotation'!F17 -> 5731741.4
A11: M6 – Go-Live | B11: Production launch, web + apps live | C11: Month 11 | D11: 0.08 | E11: =D11*'Phase Quotation'!F17 -> 3821161
A12: M7 – Final Acceptance | B12: Hypercare complete, handover signed | C12: Month 11 | D12: 0.05 | E12: =D12*'Phase Quotation'!F17 -> 2388225.6
A13: TOTAL | D13: =SUM(D5:D12) -> 1 | E13: =SUM(E5:E12) -> 47764512

Sheet Resource Plan
A1: PROJECT HORIZON — RESOURCE & PERSONNEL PLAN
A2: Meridian Retail Pvt. Ltd. | ShopSphere E-Commerce Platform | Blended India CTC rates (FY 2025-26), all figures in INR
A4: # | B4: Role / Discipline | C4: Head- count | D4: Monthly Cost-to-Co. (₹) | E4: Person- Months | F4: Total Cost (₹) | G4: Engagement Window
A5: 1 | B5: Project Manager (IT) | C5: 1 | D5: 250000 | E5: 11 | F5: =D5*E5 -> 2750000 | G5: M1–M11 (full project)
A6: 2 | B6: Business Analyst | C6: 1 | D6: 160000 | E6: 8 | F6: =D6*E6 -> 1280000 | G6: M1–M8 (front-loaded)
A7: 3 | B7: Solution / Technical Architect | C7: 1 | D7: 280000 | E7: 9 | F7: =D7*E7 -> 2520000 | G7: M1–M9
A8: 4 | B8: Scrum Master | C8: 1 | D8: 140000 | E8: 9 | F8: =D8*E8 -> 1260000 | G8: M2–M10
A9: 5 | B9: UX / UI Designer | C9: 2 | D9: 120000 | E9: 12 | F9: =D9*E9 -> 1440000 | G9: M1–M7
A10: 6 | B10: Frontend Developer (Web) | C10: 4 | D10: 130000 | E10: 28 | F10: =D10*E10 -> 3640000 | G10: M3–M9
A11: 7 | B11: Backend Developer (Microservices) | C11: 5 | D11: 150000 | E11: 38 | F11: =D11*E11 -> 5700000 | G11: M3–M10
A12: 8 | B12: Mobile Developer (iOS + Android) | C12: 3 | D12: 140000 | E12: 21 | F12: =D12*E12 -> 2940000 | G12: M3–M9
A13: 9 | B13: DevOps / SRE Engineer | C13: 2 | D13: 160000 | E13: 16 | F13: =D13*E13 -> 2560000 | G13: M2–M11
A14: 10 | B14: Data / Supply-Chain Engineer | C14: 1 | D14: 170000 | E14: 7 | F14: =D14*E14 -> 1190000 | G14: M4–M10
A15: 11 | B15: QA / Test Engineer | C15: 4 | D15: 100000 | E15: 24 | F15: =D15*E15 -> 2400000 | G15: M5–M10
A16: 12 | B16: Security & Compliance Specialist | C16: 1 | D16: 200000 | E16: 3 | F16: =D16*E16 -> 600000 | G16: M8–M10
B17: TOTAL PERSONNEL COST | C17: =SUM(C5:C16) -> 26 | E17: =SUM(E5:E16) -> 186 | F17: =SUM(F5:F16) -> 28280000
B19: Blue figures are editable assumptions (monthly CTC, person-months). All totals are live formulas.

Sheet Other Costs
A1: NON-PERSONNEL COSTS
A2: Infrastructure, tooling, integrations, security, data, marketing & launch — all figures in INR
A4: # | B4: Cost Category | C4: Description / Basis | D4: Amount (₹)
A5: 1 | B5: Cloud Infrastructure | C5: Dev/Staging/Prod on cloud; compute, DB, CDN, storage (11-mo ramp) | D5: 1800000
A6: 2 | B6: Software Licenses & Tools | C6: Jira, Confluence, Figma, GitHub Enterprise, CI/CD, APM/monitoring | D6: 650000
A7: 3 | B7: Third-Party Integrations & APIs | C7: Payment gateway, SMS/WhatsApp/email, logistics & shipping, maps | D7: 900000
A8: 4 | B8: Security Audit & Compliance | C8: VAPT, PCI-DSS readiness, DPDP Act review, source-code review | D8: 750000
A9: 5 | B9: Testing Tools & Device Lab | C9: Cross-browser cloud, load/performance tools, mobile device lab | D9: 450000
A10: 6 | B10: Data Migration & Integration | C10: Legacy catalog, customer & order migration; ERP/WMS connectors | D10: 500000
A11: 7 | B11: Marketing & Launch | C11: Digital ads, ASO/SEO, influencer, creatives, launch event | D11: 3500000
A12: 8 | B12: Training & Documentation | C12: CS/ops enablement, admin & user manuals, runbooks | D12: 300000
A13: 9 | B13: Hardware & Contingency Misc. | C13: Workstations, secure access, miscellaneous provisioning | D13: 350000
B14: TOTAL NON-PERSONNEL COST | D14: =SUM(D5:D13) -> 9200000
